clockifyclient/__init__.py
clockifyclient/api.py
clockifyclient/client.py
clockifyclient/decorators.py
clockifyclient/exceptions.py
clockifyclient/models.py
clockifyclient-0.2.3.dist-info/AUTHORS.rst
clockifyclient-0.2.3.dist-info/LICENSE
clockifyclient-0.2.3.dist-info/METADATA
clockifyclient-0.2.3.dist-info/WHEEL
clockifyclient-0.2.3.dist-info/top_level.txt
clockifyclient-0.2.3.dist-info/RECORD
