Metadata-Version: 2.1
Name: clockifyclient
Version: 0.2.3
Summary: Python client for the Clockify web API
Home-page: https://github.com/sjoerdk/clockify_api_client
Author: Sjoerd Kerkstra
Author-email: sjoerdk1@xs4all.nl
License: GNU General Public License v3
Keywords: clockifyclient
Platform: UNKNOWN
Classifier: Development Status :: 2 - Pre-Alpha
Classifier: Intended Audience :: Developers
Classifier: License :: OSI Approved :: GNU General Public License v3 (GPLv3)
Classifier: Natural Language :: English
Classifier: Programming Language :: Python :: 3.7
Requires-Dist: requests
